PointsStatistics/__init__.py
PointsStatistics/poisstatistics.py
PointsStatistic-0.1.1.dist-info/METADATA
PointsStatistic-0.1.1.dist-info/WHEEL
PointsStatistic-0.1.1.dist-info/top_level.txt
PointsStatistic-0.1.1.dist-info/RECORD
