Metadata-Version: 2.1
Name: PointsStatistic
Version: 0.1.1
Summary: Library to count POIs around reference points, and distance of the closest ones
Home-page: https://PointsStatistics.readthedocs.io/
Author: Francesco Niccolò Polinelli
Author-email: francescon.polinelli@gmail.com
License: Free for non-commercial use
Platform: UNKNOWN
Classifier: Intended Audience :: Developers
Classifier: License :: Free for non-commercial use
Classifier: Programming Language :: Python
Classifier: Programming Language :: Python :: 3
Classifier: Programming Language :: Python :: 3.6
Classifier: Programming Language :: Python :: 3.7
Classifier: Programming Language :: Python :: 3.8
Classifier: Programming Language :: Python :: 3.9
Classifier: Operating System :: OS Independent
Requires-Dist: os
Requires-Dist: time
Requires-Dist: pandas
Requires-Dist: geopandas
Requires-Dist: shapely
